workbench_cli/__init__.py
workbench_cli/auto_quote_xform.py
workbench_cli/client_helper.py
workbench_cli/config.ini
workbench_cli/file_streamer.py
workbench_cli/help_content.py
workbench_cli/README.rst
workbench_cli/repr_to_str_decorator.py
workbench_cli/version.py
workbench_cli/workbench
workbench_cli/workbench_shell.py
workbench_cli-0.3.3.data/scripts/workbench
workbench_cli-0.3.3.dist-info/DESCRIPTION.rst
workbench_cli-0.3.3.dist-info/METADATA
workbench_cli-0.3.3.dist-info/metadata.json
workbench_cli-0.3.3.dist-info/RECORD
workbench_cli-0.3.3.dist-info/top_level.txt
workbench_cli-0.3.3.dist-info/WHEEL
