Metadata-Version: 2.0
Name: workbench-cli
Version: 0.3.3
Summary: Command Line Interface for Workbench
Home-page: http://github.com/SuperCowPowers/workbench
Author: The Workbench Team
Author-email: support@supercowpowers.com
License: MIT
Keywords: workbench security python
Platform: UNKNOWN
Classifier: Development Status :: 2 - Pre-Alpha
Classifier: Intended Audience :: Developers
Classifier: License :: OSI Approved :: MIT License
Classifier: Natural Language :: English
Classifier: Programming Language :: Python :: 2.7
Requires-Dist: funcsigs
Requires-Dist: ipython
Requires-Dist: lz4
Requires-Dist: pandas
Requires-Dist: pytest
Requires-Dist: zerorpc
